pygeoid/__init__.py
pygeoid/constants.py
pygeoid/units.py
pygeoid/coordinates/__init__.py
pygeoid/coordinates/ellipsoid.py
pygeoid/coordinates/position.py
pygeoid/coordinates/transform.py
pygeoid/coordinates/test/__init__.py
pygeoid/coordinates/test/test_ellipsoid.py
pygeoid/coordinates/test/test_position.py
pygeoid/coordinates/test/test_transform.py
pygeoid/coordinates/test/data/GeodTest-short.dat.gz
pygeoid/reduction/__init__.py
pygeoid/reduction/atmosphere.py
pygeoid/reduction/ellipsoid.py
pygeoid/reduction/normal.py
pygeoid/reduction/topography.py
pygeoid/reduction/data/IAG_atmosphere_correction_table.txt
pygeoid/reduction/test/__init__.py
pygeoid/reduction/test/test_atmosphere.py
pygeoid/reduction/test/test_ellipsoid.py
pygeoid/reduction/test/test_normal.py
pygeoid/reduction/test/test_topography.py
pygeoid/reduction/test/data/Bullard_B_correction.txt
pygeoid/reduction/test/data/ussa1976_density.txt.gz
pygeoid/sharm/__init__.py
pygeoid/sharm/expand.py
pygeoid/sharm/ggm.py
pygeoid/sharm/legendre.py
pygeoid/sharm/utils.py
pygeoid/sharm/test/__init__.py
pygeoid/sharm/test/test_ggm.py
pygeoid/sharm/test/test_legendre.py
pygeoid/sharm/test/data/egm96.gfc.tar.gz
pygeoid/sharm/test/data/icgem_test_data.csv
pygeoid/simple/__init__.py
pygeoid/simple/core.py
pygeoid/simple/prism.py
pygeoid/simple/test/__init__.py
pygeoid/simple/test/test_prism.py
pygeoid-0.0.3.dist-info/METADATA
pygeoid-0.0.3.dist-info/RECORD
pygeoid-0.0.3.dist-info/WHEEL
pygeoid-0.0.3.dist-info/top_level.txt
