Metadata-Version: 2.1
Name: pygeoid
Version: 0.0.3
Summary: Local gravity field modelling with Python
Home-page: https://github.com/ioshchepkov/pygeoid
Author: Ilya Oshchepkov
Author-email: ilya.oshchepkov@gmail.com
License: MIT
Keywords: geodesy,gravimetry,geoid
Platform: UNKNOWN
Classifier: Development Status :: 1 - Planning
Classifier: Environment :: Console
Classifier: Intended Audience :: Developers
Classifier: Intended Audience :: Education
Classifier: Intended Audience :: Science/Research
Classifier: License :: OSI Approved :: MIT License
Classifier: Natural Language :: English
Classifier: Operating System :: OS Independent
Classifier: Programming Language :: Python
Classifier: Programming Language :: Python :: 3 :: Only
Classifier: Programming Language :: Python :: 3.5
Classifier: Programming Language :: Python :: 3.6
Classifier: Programming Language :: Python :: 3.7
Classifier: Topic :: Education
Classifier: Topic :: Scientific/Engineering
Requires-Python: >=3.5
Requires-Dist: numpy
Requires-Dist: scipy
Requires-Dist: pyproj
Requires-Dist: pint
Requires-Dist: pyshtools
Requires-Dist: joblib
